LICENSE.md
MANIFEST.in
README.md
setup.py
ceotr_config/__init__.py
ceotr_config/config_handler.py
ceotr_config.egg-info/PKG-INFO
ceotr_config.egg-info/SOURCES.txt
ceotr_config.egg-info/dependency_links.txt
ceotr_config.egg-info/requires.txt
ceotr_config.egg-info/top_level.txt
ceotr_config.egg-info/zip-safe
ceotr_config/template/__init__.py
ceotr_config/template/default_django_setting.yml-tpl
ceotr_config/template/default_setting.yml-tpl
test/__init__.py
test/ceotr_conifg_test/__init__.py
test/ceotr_conifg_test/tests.py
test/ceotr_conifg_test/resource/__init__.py