Metadata-Version: 2.1
Name: ceotr-config
Version: 1.0.8
Summary: Common python library for CEOTR data team
Home-page: https://gitlab.oceantrack.org/ceotr-public/ceotr_app_common/ceotr_config
Author: CEOTR
Author-email: support@ceotr.ca
License: GNU General Public License v3 (GPLv3)
Platform: UNKNOWN
License-File: LICENSE.md
